{"viewPoint":{"zoom":0.94,"width":405,"height":549,"pinBall":{"height":20,"width":20}},
"connectors":{"right":{"left":398,"top":53},
"bottom":{"left":142,"top":262},
"left":{"left":39,"top":53}},
"pins":[{"pin":"A15","left":364,"top":42,"layout":"right"},
{"pin":"A14","left":364,"top":66,"layout":"right"},
{"pin":"A13","left":364,"top":91,"layout":"right"},
{"pin":"A10","left":364,"top":115,"layout":"right"},
{"pin":"A9","left":364,"top":140,"layout":"right"},
{"pin":"A8","left":364,"top":164,"layout":"right"},
{"pin":"C11","left":364,"top":188,"layout":"right"},
{"pin":"C10","left":364,"top":213,"layout":"right"},
{"pin":"C9","left":364,"top":237,"layout":"right"},
{"pin":"C8","left":364,"top":262,"layout":"right"},
{"pin":"C7","left":364,"top":286,"layout":"right"},
{"pin":"C6","left":364,"top":311,"layout":"right"},
{"pin":"C5","left":364,"top":335,"layout":"right"},
{"pin":"C4","left":364,"top":360,"layout":"right"},
{"pin":"B15","left":364,"top":384,"layout":"right"},
{"pin":"B14","left":364,"top":408,"layout":"right"},
{"pin":"B13","left":364,"top":433,"layout":"right"},
{"pin":"3.3","left":364,"top":457,"layout":"right"},
{"pin":"VBAT","left":364,"top":482,"layout":"right"},
{"pin":"GND","left":364,"top":506,"layout":"right"},
{"pin":"A2","left":130,"top":236,"layout":"bottom"},
{"pin":"A3","left":154,"top":236,"layout":"bottom"},
{"pin":"A4","left":179,"top":236,"layout":"bottom"},
{"pin":"A5","left":203,"top":236,"layout":"bottom"},
{"pin":"A6","left":228,"top":236,"layout":"bottom"},
{"pin":"A7","left":252,"top":236,"layout":"bottom"},
{"pin":"B0","left":276,"top":236,"layout":"bottom"},
{"pin":"B1","left":301,"top":236,"layout":"bottom"},
{"pin":"B10","left":325,"top":236,"layout":"bottom"},
{"pin":"B11","left":350,"top":236,"layout":"bottom"},
{"pin":"B2","left":26,"top":42,"layout":"left"},
{"pin":"B3","left":26,"top":66,"layout":"left"},
{"pin":"B4","left":26,"top":91,"layout":"left"},
{"pin":"B5","left":26,"top":115,"layout":"left"},
{"pin":"B6","left":26,"top":140,"layout":"left"},
{"pin":"B7","left":26,"top":164,"layout":"left"},
{"pin":"B8","left":26,"top":188,"layout":"left"},
{"pin":"B9","left":26,"top":213,"layout":"left"},
{"pin":"B12","left":26,"top":237,"layout":"left"},
{"pin":"C12","left":26,"top":262,"layout":"left"},
{"pin":"C15","left":26,"top":286,"layout":"left"},
{"pin":"C0","left":26,"top":311,"layout":"left"},
{"pin":"C1","left":26,"top":335,"layout":"left"},
{"pin":"C2","left":26,"top":360,"layout":"left"},
{"pin":"C3","left":26,"top":384,"layout":"left"},
{"pin":"A0","left":26,"top":408,"layout":"left"},
{"pin":"A1","left":26,"top":433,"layout":"left"},
{"pin":"3.3","left":26,"top":457,"layout":"left"},
{"pin":"VBAT","left":26,"top":482,"layout":"left"},
{"pin":"GND","left":26,"top":506,"layout":"left"}]}